certbot_dns_oci/__init__.py
certbot_dns_oci/_internal/__init__.py
certbot_dns_oci/_internal/dns_oci.py
certbot_dns_oci-0.3.6.dist-info/LICENSE
certbot_dns_oci-0.3.6.dist-info/METADATA
certbot_dns_oci-0.3.6.dist-info/WHEEL
certbot_dns_oci-0.3.6.dist-info/entry_points.txt
certbot_dns_oci-0.3.6.dist-info/pbr.json
certbot_dns_oci-0.3.6.dist-info/top_level.txt
certbot_dns_oci-0.3.6.dist-info/RECORD
