Metadata-Version: 2.1
Name: certbot-dns-oci
Version: 0.3.6
Summary: Oracle Cloud infrastructure DNS Authenticator plugin for Certbot
Home-page: https://github.com/ITD27M01/certbot-dns-oci
Author: itd27m01
Author-email: igortiunov@gmail.com
License: MIT
Platform: UNKNOWN
Classifier: Programming Language :: Python :: 3.6
Classifier: Programming Language :: Python :: 3.8
Classifier: License :: OSI Approved :: MIT License
Classifier: Intended Audience :: System Administrators
Classifier: Environment :: Plugins
Classifier: Operating System :: OS Independent
Classifier: Topic :: Internet :: WWW/HTTP
Classifier: Topic :: Security
Classifier: Topic :: System :: Installation/Setup
Classifier: Topic :: System :: Networking
Classifier: Topic :: System :: Systems Administration
Classifier: Topic :: Utilities
Requires-Dist: zope.interface
Requires-Dist: oci (>=2.35.0)
Requires-Dist: acme (>=1.13.0)
Requires-Dist: certbot (<=1.15.0)
